btog.v
module binarytogray(b0,b1,b2,b3,g0,g1,g2,g3);
input b0,b1,b2,b3;
output g0,g1,g2,g3;
assign g3=b3;
xor (g2,b3,b2),(g1,b2,b1),(g0,b1,b0);
endmodule

btog_tb.v
module binarytogray_tb;
wire g0,g1,g2,g3;
reg b0,b1,b2,b3;
binarytogray gate(.b0(b0),.b1(b1),.b2(b2),.b3(b3),.g0(g0),.g1(g1),.g2(g2),.g3(g3));
initial
begin
$monitor("%b %b %b %b  %b %b %b %b",b3,b2,b1,b0,g3,g2,g1,g0);
$dumpfile("binarytogray_tb.vcd");
$dumpvars(0,binarytogray_tb);
b3=0;
b2=0;
b1=0;
b0=0;
#2
#150 $finish;
end
always #10 b0=!b0;
always #20 b1=!b1;
always #40 b2=!b2;
always #80 b3=!b3;
endmodule

binarytogray_tb.vcd
$date
	Fri Aug 05 09:23:58 2022
$end
$version
	Icarus Verilog
$end
$timescale
	1s
$end
$scope module binarytogray_tb $end
$var wire 1 ! g3 $end
$var wire 1 " g2 $end
$var wire 1 # g1 $end
$var wire 1 $ g0 $end
$var reg 1 % b0 $end
$var reg 1 & b1 $end
$var reg 1 ' b2 $end
$var reg 1 ( b3 $end
$scope module gate $end
$var wire 1 % b0 $end
$var wire 1 & b1 $end
$var wire 1 ' b2 $end
$var wire 1 ( b3 $end
$var wire 1 $ g0 $end
$var wire 1 # g1 $end
$var wire 1 " g2 $end
$var wire 1 ! g3 $end
$upscope $end
$upscope $end
$enddefinitions $end
$comment Show the parameter values. $end
$dumpall
$end
#0
$dumpvars
0(
0'
0&
0%
0$
0#
0"
0!
$end
#10
1$
1%
#20
1#
0%
1&
#30
0$
1%
#40
1"
0%
0&
1'
#50
1$
1%
#60
0#
0%
1&
#70
0$
1%
#80
0%
0&
0'
1!
1(
#90
1$
1%
#100
1#
0%
1&
#110
0$
1%
#120
0"
0%
0&
1'
#130
1$
1%
#140
0#
0%
1&
#150
0$
1%
