bool3.v
module booleanfunc(a,b,c,d,y);
input a,b,c,d;
output y;
assign y=(a&!c)|(!b&d)|(!a&c&d)|(a&b&c&d);
endmodule;

bool(1)_tb.v
module bool_tb;
wire y;
reg a,b,c,d;
booleanfunc gate(.a(a),.b(b),.c(c),.d(d),.y(y));
initial 
begin
$monitor("%b %b %b %b %b",a,b,c,d,y);
$dumpfile("bool_tb.vcd");
$dumpvars(0,bool_tb);
a=0;
b=0;
c=0;
d=0;
#2
#150 $finish;
end
always #80 a=!a;
always #40 b=!b;
always #20 c=!c;
always #10 d=!d;
endmodule

bool_tb.vcd
$date
	Thu Aug 04 23:10:24 2022
$end
$version
	Icarus Verilog
$end
$timescale
	1s
$end
$scope module bool_tb $end
$var wire 1 ! y $end
$var reg 1 " a $end
$var reg 1 # b $end
$var reg 1 $ c $end
$var reg 1 % d $end
$scope module gate $end
$var wire 1 " a $end
$var wire 1 # b $end
$var wire 1 $ c $end
$var wire 1 % d $end
$var wire 1 ! y $end
$upscope $end
$upscope $end
$enddefinitions $end
$comment Show the parameter values. $end
$dumpall
$end
#0
$dumpvars
0%
0$
0#
0"
0!
$end
#10
1!
1%
#20
0!
0%
1$
#30
1!
1%
#40
0!
0%
0$
1#
#50
1%
#60
0%
1$
#70
1!
1%
#80
0%
0$
0#
1"
#90
1%
#100
0!
0%
1$
#110
1!
1%
#120
0%
0$
1#
#130
1%
#140
0!
0%
1$
#150
1!
1%
