demux.v
module demux(d0,d1,d2,d3,d,s0,s1);
input s0,s1,d;
output d0,d1,d2,d3;
wire out_not1,out_not2;
not(out_not1,s1),(out_not2,s0);
and(d0,out_not1,out_not2,d),(d1,out_not2,s1,d),(d2,out_not1,s0,d),(d3,s1,s0,d);
endmodule

demux_tb.v
module demux_tb;
reg d,s0,s1;
wire d0,d1,d2,d3;

demux gate(.d0(d0),.d1(d1),.d2(d2),.d3(d3),.s0(s0),.s1(s1),.d(d));
initial begin
    $dumpfile("demux_tb.vcd");
    $dumpvars(0,demux_tb);
    $display("S0 | S1 | D || D0 | D1 | D2 | D3");
    $display("--------------------------------");

    $monitor("%b  | %b  | %b  || %b  | %b  | %b  | %b",s0,s1,d,d0,d1,d2,d3);

    d=0;
    s0=0;
    s1=0;
    #9
    #70 $finish;
end
always #40 s0=!s0;
always #20 s1=!s1;
always #10 d=!d;
endmodule

demux_tb.vcd
$date
	Fri Aug 05 09:47:41 2022
$end
$version
	Icarus Verilog
$end
$timescale
	1s
$end
$scope module demux_tb $end
$var wire 1 ! d3 $end
$var wire 1 " d2 $end
$var wire 1 # d1 $end
$var wire 1 $ d0 $end
$var reg 1 % d $end
$var reg 1 & s0 $end
$var reg 1 ' s1 $end
$scope module gate $end
$var wire 1 % d $end
$var wire 1 $ d0 $end
$var wire 1 # d1 $end
$var wire 1 " d2 $end
$var wire 1 ! d3 $end
$var wire 1 ( out_not1 $end
$var wire 1 ) out_not2 $end
$var wire 1 & s0 $end
$var wire 1 ' s1 $end
$upscope $end
$upscope $end
$enddefinitions $end
$comment Show the parameter values. $end
$dumpall
$end
#0
$dumpvars
1)
1(
0'
0&
0%
0$
0#
0"
0!
$end
#10
1$
1%
#20
0$
0(
0%
1'
#30
1#
1%
#40
1(
0#
0)
0%
0'
1&
#50
1"
1%
#60
0"
0(
0%
1'
#70
1!
1%
