fullsubtractor1.v
module fullsubtractor(a,b,bin,d,bout);
input a,b,bin;
output d,bout;
assign d=a^b^bin;
assign bout=(!a&bin)|(!a&b)|(b&bin);
endmodule

fullsubtractor_tb.v
module fullsubtractor_tb;
wire d,bout;
reg a,b,bin;
fullsubtractor gate(.a(a),.b(b),.bin(bin),.d(d),.bout(bout));
initial
begin
$monitor("%b %b %b %b %b",a,b,bin,d,bout);
$dumpfile("fullsubtractor_tb.vcd");
$dumpvars(0,fullsubtractor_tb);
a=0;
b=0;
bin=0;
#2
#70 $finish;
end
always #40 a=!a;
always #20 b=!b;
always #10 bin=!bin;
endmodule

fullsubtractor_tb.vcd
$date
	Thu Aug 04 01:53:00 2022
$end
$version
	Icarus Verilog
$end
$timescale
	1s
$end
$scope module fullsubtractor_tb $end
$var wire 1 ! d $end
$var wire 1 " bout $end
$var reg 1 # a $end
$var reg 1 $ b $end
$var reg 1 % bin $end
$scope module gate $end
$var wire 1 # a $end
$var wire 1 $ b $end
$var wire 1 % bin $end
$var wire 1 " bout $end
$var wire 1 ! d $end
$upscope $end
$upscope $end
$enddefinitions $end
$comment Show the parameter values. $end
$dumpall
$end
#0
$dumpvars
0%
0$
0#
0"
0!
$end
#10
1"
1!
1%
#20
0%
1$
#30
0!
1%
#40
0"
1!
0%
0$
1#
#50
0!
1%
#60
0%
1$
#70
1"
1!
1%
