fulladd.v
module fulladder(a,b,cin,s,cout);
input a,b,cin;
output s,cout;
wire out_xor1,out_and1,out_and2;
xor (out_xor1,a,b),(s,out_xor1,cin);
and (out_and1,a,b);
and (out_and2,cin,out_xor1);
or (cout,out_and1,out_and2);
endmodule

fulladd_tb.v
module fulladder_tb;
wire s,cout;
reg a,b,cin;
fulladder gate(.a(a),.b(b),.cin(cin),.s(s),.cout(cout));
initial
begin
$monitor("%b %b %b -> %b %b",a,b,cin,s,cout);
$dumpfile("fulladder_tb.vcd");
$dumpvars(0,fulladder_tb);
a=0;
b=0;
cin=0;
#2
#70 $finish;
end
always #40 a=!a;
always #20 b=!b;
always #10 cin=!cin;
endmodule

fulladder_tb.vcd
$date
	Fri Aug 05 09:19:39 2022
$end
$version
	Icarus Verilog
$end
$timescale
	1s
$end
$scope module fulladder_tb $end
$var wire 1 ! s $end
$var wire 1 " cout $end
$var reg 1 # a $end
$var reg 1 $ b $end
$var reg 1 % cin $end
$scope module gate $end
$var wire 1 # a $end
$var wire 1 $ b $end
$var wire 1 % cin $end
$var wire 1 " cout $end
$var wire 1 & out_and1 $end
$var wire 1 ' out_and2 $end
$var wire 1 ( out_xor1 $end
$var wire 1 ! s $end
$upscope $end
$upscope $end
$enddefinitions $end
$comment Show the parameter values. $end
$dumpall
$end
#0
$dumpvars
0(
0'
0&
0%
0$
0#
0"
0!
$end
#10
1!
1%
#20
1(
0%
1$
#30
1"
0!
1'
1%
#40
0"
1!
0'
0%
0$
1#
#50
1"
0!
1'
1%
#60
0'
0(
1&
0%
1$
#70
1!
1%
