gtob.v
module graytobinary(b0,b1,b2,b3,g0,g1,g2,g3);
output b0,b1,b2,b3;
input g0,g1,g2,g3;
assign b3=g3;
xor (b2,g3,g2),(b1,b2,g1),(b0,b1,g0);
endmodule

gtob_tb.v
module graytobinary_tb;
reg g0,g1,g2,g3;
wire b0,b1,b2,b3;
graytobinary gate(.b0(b0),.b1(b1),.b2(b2),.b3(b3),.g0(g0),.g1(g1),.g2(g2),.g3(g3));
initial
begin
$monitor("%b %b %b %b  %b %b %b %b",g3,g2,g1,g0,b3,b2,b1,b0);
$dumpfile("graytobinary_tb.vcd");
$dumpvars(0,graytobinary_tb);
g3=0;
g2=0;
g1=0;
g0=0;
#2
#150 $finish;
end
always #10 g0=!g0;
always #20 g1=!g1;
always #40 g2=!g2;
always #80 g3=!g3;
endmodule

graytobinary_tb.vcd
$date
	Fri Aug 05 09:28:45 2022
$end
$version
	Icarus Verilog
$end
$timescale
	1s
$end
$scope module graytobinary_tb $end
$var wire 1 ! b3 $end
$var wire 1 " b2 $end
$var wire 1 # b1 $end
$var wire 1 $ b0 $end
$var reg 1 % g0 $end
$var reg 1 & g1 $end
$var reg 1 ' g2 $end
$var reg 1 ( g3 $end
$scope module gate $end
$var wire 1 $ b0 $end
$var wire 1 # b1 $end
$var wire 1 " b2 $end
$var wire 1 ! b3 $end
$var wire 1 % g0 $end
$var wire 1 & g1 $end
$var wire 1 ' g2 $end
$var wire 1 ( g3 $end
$upscope $end
$upscope $end
$enddefinitions $end
$comment Show the parameter values. $end
$dumpall
$end
#0
$dumpvars
0(
0'
0&
0%
0$
0#
0"
0!
$end
#10
1$
1%
#20
1#
0%
1&
#30
0$
1%
#40
1$
1"
0%
0&
1'
#50
0$
1%
#60
0#
0%
1&
#70
1$
1%
#80
1#
0%
0&
0'
1!
1(
#90
0$
1%
#100
0#
0%
1&
#110
1$
1%
#120
0$
0"
0%
0&
1'
#130
1$
1%
#140
1#
0%
1&
#150
0$
1%
